[{"Licence number":"LIQC300226271","Licence name":"Castle Hill Country Club Ltd","Address":"RMB 49 Windsor Rd","Suburb":"BAULKHAM HILLS","Postcode":2153,"Latitude":-33.7277,"Longitude":150.9627,"lgaIdNSW":"17420","EGMs":17},{"Licence number":"LIQC300226298","Licence name":"Castle Hill Bowling Club Ltd","Address":"79 Castle St","Suburb":"CASTLE HILL","Postcode":2154,"Latitude":-33.7259,"Longitude":150.9983,"lgaIdNSW":"17420","EGMs":14},{"Licence number":"LIQC300226301","Licence name":"Castle Hill RSL Club","Address":"77 CASTLE ST","Suburb":"CASTLE HILL","Postcode":2154,"Latitude":-33.7266,"Longitude":150.9969,"lgaIdNSW":"17420","EGMs":312},{"Licence number":"LIQC300227685","Licence name":"The Hills District Bowling Club Ltd","Address":"6-12 Jenner St","Suburb":"BAULKHAM HILLS","Postcode":2153,"Latitude":-33.7601,"Longitude":150.9937,"lgaIdNSW":"17420","EGMs":49},{"Licence number":"LIQC300231100","Licence name":"Dural Country Club","Address":"662A Old Northern Rd","Suburb":"DURAL","Postcode":2158,"Latitude":-33.676,"Longitude":151.0252,"lgaIdNSW":"17420","EGMs":47},{"Licence number":"LIQC300231550","Licence name":"Baulkham Hills Sports Club","Address":"11 Renown Rd","Suburb":"BAULKHAM HILLS","Postcode":2153,"Latitude":-33.7631,"Longitude":151.0043,"lgaIdNSW":"17420","EGMs":144},{"Licence number":"LIQC300243664","Licence name":"Glenorie RSL Club","Address":"3 POST OFFICE RD","Suburb":"GLENORIE","Postcode":2157,"Latitude":-33.6013,"Longitude":151.0056,"lgaIdNSW":"17420","EGMs":41}]
